avatar/__init__.py
avatar/admin.py
avatar/apps.py
avatar/conf.py
avatar/forms.py
avatar/models.py
avatar/providers.py
avatar/signals.py
avatar/urls.py
avatar/utils.py
avatar/views.py
avatar/api/__init__.py
avatar/api/apps.py
avatar/api/conf.py
avatar/api/serializers.py
avatar/api/shortcut.py
avatar/api/signals.py
avatar/api/urls.py
avatar/api/utils.py
avatar/api/views.py
avatar/api/migrations/__init__.py
avatar/locale/de/LC_MESSAGES/django.mo
avatar/locale/de/LC_MESSAGES/django.po
avatar/locale/es/LC_MESSAGES/django.mo
avatar/locale/es/LC_MESSAGES/django.po
avatar/locale/fa/LC_MESSAGES/django.mo
avatar/locale/fa/LC_MESSAGES/django.po
avatar/locale/fr/LC_MESSAGES/django.mo
avatar/locale/fr/LC_MESSAGES/django.po
avatar/locale/it/LC_MESSAGES/django.mo
avatar/locale/it/LC_MESSAGES/django.po
avatar/locale/ja/LC_MESSAGES/django.mo
avatar/locale/ja/LC_MESSAGES/django.po
avatar/locale/nl/LC_MESSAGES/django.mo
avatar/locale/nl/LC_MESSAGES/django.po
avatar/locale/pl/LC_MESSAGES/django.mo
avatar/locale/pl/LC_MESSAGES/django.po
avatar/locale/pt_BR/LC_MESSAGES/django.mo
avatar/locale/pt_BR/LC_MESSAGES/django.po
avatar/locale/ru/LC_MESSAGES/django.mo
avatar/locale/ru/LC_MESSAGES/django.po
avatar/locale/zh_CN/LC_MESSAGES/django.mo
avatar/locale/zh_CN/LC_MESSAGES/django.po
avatar/management/__init__.py
avatar/management/commands/__init__.py
avatar/management/commands/rebuild_avatars.py
avatar/migrations/0001_initial.py
avatar/migrations/0002_add_verbose_names_to_avatar_fields.py
avatar/migrations/0003_auto_20170827_1345.py
avatar/migrations/__init__.py
avatar/templates/avatar/add.html
avatar/templates/avatar/avatar_tag.html
avatar/templates/avatar/base.html
avatar/templates/avatar/change.html
avatar/templates/avatar/confirm_delete.html
avatar/templates/avatar/initials.html
avatar/templates/notification/avatar_friend_updated/full.txt
avatar/templates/notification/avatar_friend_updated/notice.html
avatar/templates/notification/avatar_updated/full.txt
django_avatar-8.0.0.dist-info/LICENSE.txt
django_avatar-8.0.0.dist-info/METADATA
django_avatar-8.0.0.dist-info/WHEEL
django_avatar-8.0.0.dist-info/top_level.txt
django_avatar-8.0.0.dist-info/RECORD
