Metadata-Version: 2.1
Name: django-avatar
Version: 8.0.0
Summary: A Django app for handling user avatars
Author-email: Eric Florenzano <floguy@gmail.com>
Maintainer-email: Johannes Wilm <johannes@fiduswriter.org>
License: BSD-4-Clause
Project-URL: homepage, https://github.com/jazzband/django-avatar
Project-URL: repository, https://github.com/jazzband/django-avatar
Project-URL: documentation, https://django-avatar.readthedocs.io
Keywords: avatar,django
Classifier: Development Status :: 5 - Production/Stable
Classifier: Environment :: Web Environment
Classifier: Framework :: Django
Classifier: Intended Audience :: Developers
Classifier: Framework :: Django
Classifier: Framework :: Django :: 3.2
Classifier: Framework :: Django :: 4.1
Classifier: Framework :: Django :: 4.2
Classifier: License :: OSI Approved :: BSD License
Classifier: Operating System :: OS Independent
Classifier: Programming Language :: Python
Classifier: Programming Language :: Python :: 3.7
Classifier: Programming Language :: Python :: 3.8
Classifier: Programming Language :: Python :: 3.9
Classifier: Programming Language :: Python :: 3.10
Classifier: Programming Language :: Python :: 3.11
License-File: LICENSE.txt
Requires-Dist: Pillow>=10.0.1
Requires-Dist: django-appconf>=1.0.5
Requires-Dist: dnspython>=2.3.0
